model_lancet/__init__.py
model_lancet/torch_attribute2buffer.py
model_lancet/torch_model_lancet.py
model_lancet-0.1.1.dist-info/LICENSE
model_lancet-0.1.1.dist-info/METADATA
model_lancet-0.1.1.dist-info/WHEEL
model_lancet-0.1.1.dist-info/top_level.txt
model_lancet-0.1.1.dist-info/RECORD
