Metadata-Version: 2.1
Name: model-lancet
Version: 0.1.1
Summary: A tool for non-invasive modification of pytorch model functions
Home-page: UNKNOWN
Author: richard tong
Author-email: richardt@graphcore.ai
License: UNKNOWN
Platform: UNKNOWN
Classifier: Programming Language :: Python :: 3
Classifier: License :: OSI Approved :: MIT License
Classifier: Operating System :: OS Independent
License-File: LICENSE
